rimu/__init__.py
rimu/blockattributes.py
rimu/delimitedblocks.py
rimu/document.py
rimu/expansion.py
rimu/io.py
rimu/lineblocks.py
rimu/lists.py
rimu/macros.py
rimu/options.py
rimu/quotes.py
rimu/replacements.py
rimu/rimu.py
rimu/spans.py
rimu/utils.py
rimuc/__init__.py
rimuc/__main__.py
rimuc/resources.py
rimuc/rimuc.py
rimu-11.4.2.dist-info/LICENSE
rimu-11.4.2.dist-info/METADATA
rimu-11.4.2.dist-info/WHEEL
rimu-11.4.2.dist-info/entry_points.txt
rimu-11.4.2.dist-info/top_level.txt
rimu-11.4.2.dist-info/RECORD
