Metadata-Version: 2.1
Name: rimu
Version: 11.4.2
Summary: Rimu is a readable-text to HTML markup language inspired by AsciiDoc and Markdown.
Home-page: https://github.com/srackham/rimu-py
Author: Stuart Rackham
Author-email: srackham@gmail.com
License: MIT
Project-URL: Documentation, https://srackham.github.io/rimu/
Project-URL: Source, https://github.com/srackham/rimu-py
Keywords: rimu markdown asciidoc
Classifier: Programming Language :: Python :: 3
Classifier: License :: OSI Approved :: MIT License
Classifier: Operating System :: OS Independent
Requires-Python: >=3.8
License-File: LICENSE
